{
    "3100": "7EEpIeXhO54_74.gif",
    "3101": "jhuRtkqUSSI_42.gif",
    "3102": "jhuRtkqUSSI_42.gif",
    "3103": "jhuRtkqUSSI_42.gif",
    "3104": "jhuRtkqUSSI_42.gif",
    "3105": "8VPiqCCOPWg_206.gif",
    "3106": "8VPiqCCOPWg_206.gif",
    "3107": "jhuRtkqUSSI_42.gif",
    "3108": "jhuRtkqUSSI_42.gif",
    "3109": "jhuRtkqUSSI_42.gif",
    "3110": "jhuRtkqUSSI_42.gif",
    "3111": "jhuRtkqUSSI_42.gif",
    "3112": "OW_iCiS_U4Y_126.gif",
    "3113": "bNuRrXSjJl0_258.gif",
    "3114": "jhuRtkqUSSI_42.gif",
    "3115": "jhuRtkqUSSI_42.gif",
    "3116": "jhuRtkqUSSI_42.gif",
    "3117": "OW_iCiS_U4Y_126.gif",
    "3118": "L5nqeFWufrE_28.gif",
    "3119": "jhuRtkqUSSI_42.gif",
    "3120": "jhuRtkqUSSI_2.gif",
    "3121": "OW_iCiS_U4Y_126.gif",
    "3122": "8VPiqCCOPWg_232.gif",
    "3123": "ILeNuidJc00_36.gif",
    "3124": "YkqO2oi9SIk_66.gif",
    "3125": "jhuRtkqUSSI_42.gif",
    "3126": "8VPiqCCOPWg_232.gif",
    "3127": "jhuRtkqUSSI_42.gif",
    "3128": "jhuRtkqUSSI_42.gif",
    "3129": "jhuRtkqUSSI_42.gif",
    "3130": "bNuRrXSjJl0_258.gif",
    "3131": "jhuRtkqUSSI_42.gif",
    "3132": "jhuRtkqUSSI_42.gif",
    "3133": "jhuRtkqUSSI_42.gif",
    "3134": "OW_iCiS_U4Y_126.gif",
    "3135": "8VPiqCCOPWg_206.gif",
    "3136": "8VPiqCCOPWg_206.gif",
    "3137": "jhuRtkqUSSI_42.gif",
    "3138": "jhuRtkqUSSI_42.gif",
    "3139": "jhuRtkqUSSI_42.gif",
    "3140": "jhuRtkqUSSI_42.gif",
    "3141": "7EEpIeXhO54_74.gif",
    "3142": "8VPiqCCOPWg_206.gif",
    "3143": "8VPiqCCOPWg_206.gif",
    "3144": "OW_iCiS_U4Y_189.gif",
    "3145": "9uitA8tmSfE_240.gif",
    "3146": "bNuRrXSjJl0_258.gif",
    "3147": "jhuRtkqUSSI_42.gif",
    "3148": "OW_iCiS_U4Y_126.gif",
    "3149": "L5nqeFWufrE_58.gif"
}